{
    "swagger": "2.0",
    "info": {
        "version": "1.0.0",
        "title": "REST API",
        "description": ""
    },
    "host": "localhost:3000",
    "basePath": "/",
    "schemes": [
        "http"
    ],
    "paths": {
        "/api/projections/": {
            "get": {
                "description": "",
                "responses": {
                    "200": {
                        "description": "OK"
                    },
                    "500": {
                        "description": "Internal Server Error"
                    }
                }
            },
            "post": {
                "description": "",
                "responses": {
                    "201": {
                        "description": "Created"
                    },
                    "500": {
                        "description": "Internal Server Error"
                    }
                }
            }
        },
        "/api/projections/{projectionId}": {
            "get": {
                "description": "",
                "parameters": [
                    {
                        "name": "projectionId",
                        "in": "path",
                        "required": true,
                        "type": "string"
                    }
                ],
                "responses": {
                    "200": {
                        "description": "OK"
                    },
                    "404": {
                        "description": "Not Found"
                    },
                    "500": {
                        "description": "Internal Server Error"
                    }
                }
            },
            "put": {
                "description": "",
                "parameters": [
                    {
                        "name": "projectionId",
                        "in": "path",
                        "required": true,
                        "type": "string"
                    }
                ],
                "responses": {
                    "200": {
                        "description": "OK"
                    },
                    "404": {
                        "description": "Not Found"
                    },
                    "500": {
                        "description": "Internal Server Error"
                    }
                }
            },
            "delete": {
                "description": "",
                "parameters": [
                    {
                        "name": "projectionId",
                        "in": "path",
                        "required": true,
                        "type": "string"
                    }
                ],
                "responses": {
                    "200": {
                        "description": "OK"
                    },
                    "404": {
                        "description": "Not Found"
                    },
                    "500": {
                        "description": "Internal Server Error"
                    }
                }
            }
        },
        "/api/projections/{projectionId}/bookings": {
            "get": {
                "description": "",
                "parameters": [
                    {
                        "name": "projectionId",
                        "in": "path",
                        "required": true,
                        "type": "string"
                    }
                ],
                "responses": {
                    "200": {
                        "description": "OK"
                    },
                    "500": {
                        "description": "Internal Server Error"
                    }
                }
            },
            "post": {
                "description": "",
                "parameters": [
                    {
                        "name": "projectionId",
                        "in": "path",
                        "required": true,
                        "type": "string"
                    }
                ],
                "responses": {
                    "201": {
                        "description": "Created"
                    },
                    "500": {
                        "description": "Internal Server Error"
                    }
                }
            }
        },
        "/api/projections/{projectionId}/bookings/{bookingId}": {
            "get": {
                "description": "",
                "parameters": [
                    {
                        "name": "projectionId",
                        "in": "path",
                        "required": true,
                        "type": "string"
                    },
                    {
                        "name": "bookingId",
                        "in": "path",
                        "required": true,
                        "type": "string"
                    }
                ],
                "responses": {
                    "200": {
                        "description": "OK"
                    },
                    "404": {
                        "description": "Not Found"
                    },
                    "500": {
                        "description": "Internal Server Error"
                    }
                }
            },
            "put": {
                "description": "",
                "parameters": [
                    {
                        "name": "projectionId",
                        "in": "path",
                        "required": true,
                        "type": "string"
                    },
                    {
                        "name": "bookingId",
                        "in": "path",
                        "required": true,
                        "type": "string"
                    }
                ],
                "responses": {
                    "200": {
                        "description": "OK"
                    },
                    "404": {
                        "description": "Not Found"
                    },
                    "500": {
                        "description": "Internal Server Error"
                    }
                }
            },
            "delete": {
                "description": "",
                "parameters": [
                    {
                        "name": "projectionId",
                        "in": "path",
                        "required": true,
                        "type": "string"
                    },
                    {
                        "name": "bookingId",
                        "in": "path",
                        "required": true,
                        "type": "string"
                    }
                ],
                "responses": {
                    "200": {
                        "description": "OK"
                    },
                    "404": {
                        "description": "Not Found"
                    },
                    "500": {
                        "description": "Internal Server Error"
                    }
                }
            }
        }
    }
}
